{
  "beneficiaries": [
    {
      "gender": "Male",
      "goats": 64,
      "id": "upload-1771400621250-0",
      "name": "NKETINI LEARAMAN",
      "nationalId": "30183615",
      "sheep": 75
    },
    {
      "gender": "Male",
      "goats": 69,
      "id": "upload-1771400621250-1",
      "name": "IKARI LESAMANA ",
      "nationalId": "37088968",
      "sheep": 72
    },
    {
      "gender": "Male",
      "goats": 75,
      "id": "upload-1771400621250-2",
      "name": "NKESHURO LEMPAILA",
      "nationalId": "4194072",
      "sheep": 76
    },
    {
      "gender": "Male",
      "goats": 73,
      "id": "upload-1771400621250-3",
      "name": "LOIRAGIE LENTOIJONI",
      "nationalId": "31066037",
      "sheep": 74
    },
    {
      "gender": "Male",
      "goats": 66,
      "id": "upload-1771400621250-4",
      "name": "SALANI LENANGERISHO",
      "nationalId": "2371365",
      "sheep": 71
    },
    {
      "gender": "Female",
      "goats": 72,
      "id": "upload-1771400621250-5",
      "name": "RIYANAE LENTUKUNYE",
      "nationalId": "N/A",
      "sheep": 73
    },
    {
      "gender": "Female",
      "goats": 76,
      "id": "upload-1771400621250-6",
      "name": "SENIKI LEMPAILA",
      "nationalId": "N/A",
      "sheep": 77
    },
    {
      "gender": "Female",
      "goats": 73,
      "id": "upload-1771400621250-7",
      "name": "MASAILI LEOKOYA",
      "nationalId": "N/A",
      "sheep": 74
    },
    {
      "gender": "Female",
      "goats": 57,
      "id": "upload-1771400621250-8",
      "name": "SARANDA LENAREU",
      "nationalId": "N/A",
      "sheep": 72
    },
    {
      "gender": "Female",
      "goats": 81,
      "id": "upload-1771400621250-9",
      "name": "LEMANTEN LESAMANA",
      "nationalId": "26702417",
      "sheep": 75
    },
    {
      "gender": "Male",
      "goats": 69,
      "id": "upload-1771400621250-10",
      "name": "KUTUKE LENTIRO",
      "nationalId": "29948207",
      "sheep": 73
    },
    {
      "gender": "Male",
      "goats": 75,
      "id": "upload-1771400621250-11",
      "name": "LMAKAUS LEROSION",
      "nationalId": "42399508",
      "sheep": 66
    },
    {
      "gender": "Female",
      "goats": 69,
      "id": "upload-1771400621250-12",
      "name": "Ritao Lentoijoni",
      "nationalId": "40232218",
      "sheep": 50
    },
    {
      "gender": "Female",
      "goats": 74,
      "id": "upload-1771400621250-13",
      "name": "Maasai Lentoijoni",
      "nationalId": "40319209",
      "sheep": 65
    },
    {
      "gender": "Female",
      "goats": 73,
      "id": "upload-1771400621250-14",
      "name": "Nasampai Lerapayo",
      "nationalId": "29941821",
      "sheep": 74
    },
    {
      "gender": "Male",
      "goats": 71,
      "id": "upload-1771400621250-15",
      "name": "MEJIS LONGORKOI",
      "nationalId": "20221945",
      "sheep": 72
    },
    {
      "gender": "Male",
      "goats": 72,
      "id": "upload-1771400621250-16",
      "name": "LETIRIN LENTIRO",
      "nationalId": "26698999",
      "sheep": 73
    },
    {
      "gender": "Male",
      "goats": 70,
      "id": "upload-1771400621250-17",
      "name": "LEJIYON LOLWERIKOI",
      "nationalId": "20704778",
      "sheep": 63
    },
    {
      "gender": "Male",
      "goats": 75,
      "id": "upload-1771400621250-18",
      "name": "LOILIAPAU LEROSION",
      "nationalId": "3116050",
      "sheep": 73
    },
    {
      "gender": "Female",
      "goats": 73,
      "id": "upload-1771400621250-19",
      "name": "Ntiwai Lentukunye",
      "nationalId": "636613495",
      "sheep": 61
    },
    {
      "gender": "Female",
      "goats": 73,
      "id": "upload-1771400621250-20",
      "name": "Mpesina Lentunkunya",
      "nationalId": "40232120",
      "sheep": 74
    },
    {
      "gender": "Male",
      "goats": 74,
      "id": "upload-1771400621250-21",
      "name": "Apia Lentoijoni",
      "nationalId": "35894643",
      "sheep": 75
    },
    {
      "gender": "Male",
      "goats": 71,
      "id": "upload-1771400621250-22",
      "name": "Seli Lenareu",
      "nationalId": "20392148",
      "sheep": 72
    },
    {
      "gender": "Male",
      "goats": 72,
      "id": "upload-1771400621250-23",
      "name": "Michael Lentoijoni",
      "nationalId": "34459841",
      "sheep": 73
    },
    {
      "gender": "Male",
      "goats": 73,
      "id": "upload-1771400621250-24",
      "name": "Lemuntet Lekodonyo",
      "nationalId": "26706579",
      "sheep": 74
    },
    {
      "gender": "Male",
      "goats": 70,
      "id": "upload-1771400621250-25",
      "name": "Kutana Lenanosho",
      "nationalId": "26701444",
      "sheep": 71
    },
    {
      "gender": "Female",
      "goats": 72,
      "id": "upload-1771400621250-26",
      "name": "Jalima Lentoijoni",
      "nationalId": "34110501",
      "sheep": 73
    },
    {
      "gender": "Female",
      "goats": 72,
      "id": "upload-1771400621250-27",
      "name": "Lilian Lentukunya",
      "nationalId": "40232141",
      "sheep": 73
    },
    {
      "gender": "Female",
      "goats": 75,
      "id": "upload-1771400621250-28",
      "name": "Saranda Lenarru",
      "nationalId": "34166863",
      "sheep": 76
    },
    {
      "gender": "Male",
      "goats": 71,
      "id": "upload-1771400621250-29",
      "name": "PITIYIO LESARGE ",
      "nationalId": "4200137",
      "sheep": 72
    },
    {
      "gender": "Male",
      "goats": 74,
      "id": "upload-1771400621250-30",
      "name": "LUMPEYIAN LEKAASO",
      "nationalId": "27178661",
      "sheep": 75
    },
    {
      "gender": "Male",
      "goats": 73,
      "id": "upload-1771400621250-31",
      "name": "KAMPARIN LEKORPITA",
      "nationalId": "26647529",
      "sheep": 74
    },
    {
      "gender": "Female",
      "goats": 72,
      "id": "upload-1771400621250-32",
      "name": "Beleon Lenareu",
      "nationalId": "26706628",
      "sheep": 73
    },
    {
      "gender": "Female",
      "goats": 70,
      "id": "upload-1771400621250-33",
      "name": "Piriro Lattankwas",
      "nationalId": "35894941",
      "sheep": 71
    },
    {
      "gender": "Female",
      "goats": 76,
      "id": "upload-1771400621250-34",
      "name": "Sesian Lepalo",
      "nationalId": "40232293",
      "sheep": 77
    },
    {
      "gender": "Female",
      "goats": 73,
      "id": "upload-1771400621250-35",
      "name": "Ntairiani Lenawoisho",
      "nationalId": "34123198",
      "sheep": 74
    },
    {
      "gender": "Male",
      "goats": 71,
      "id": "upload-1771400621250-36",
      "name": "SANATEA LOLOKER ",
      "nationalId": "36795067",
      "sheep": 72
    },
    {
      "gender": "Male",
      "goats": 74,
      "id": "upload-1771400621250-37",
      "name": "SANATEA LOLOKER ",
      "nationalId": "36795067",
      "sheep": 75
    },
    {
      "gender": "Male",
      "goats": 72,
      "id": "upload-1771400621250-38",
      "name": "LKIKAANGO LEKIRIMANTO",
      "nationalId": "20384920",
      "sheep": 73
    },
    {
      "gender": "Male",
      "goats": 70,
      "id": "upload-1771400621250-39",
      "name": "RAMITA LOLDOMET",
      "nationalId": "30569782",
      "sheep": 71
    },
    {
      "gender": "Male",
      "goats": 75,
      "id": "upload-1771400621250-40",
      "name": "EWOI LETIPO",
      "nationalId": "30569782",
      "sheep": 76
    },
    {
      "gender": "Female",
      "goats": 73,
      "id": "upload-1771400621250-41",
      "name": "NJMURES LEMPAILA ",
      "nationalId": "31652370",
      "sheep": 74
    },
    {
      "gender": "Female",
      "goats": 74,
      "id": "upload-1771400621250-42",
      "name": "Salinta Lentoijoni",
      "nationalId": "28766658",
      "sheep": 75
    },
    {
      "gender": "Female",
      "goats": 71,
      "id": "upload-1771400621250-43",
      "name": "NCHULUG LEKERPEES ",
      "nationalId": "20346015",
      "sheep": 72
    },
    {
      "gender": "Female",
      "goats": 72,
      "id": "upload-1771400621250-44",
      "name": "KITONI LOKUPANA ",
      "nationalId": "299410401",
      "sheep": 73
    },
    {
      "gender": "Female",
      "goats": 73,
      "id": "upload-1771400621250-45",
      "name": "RESMAS LETININA",
      "nationalId": "25609664",
      "sheep": 74
    },
    {
      "gender": "Male",
      "goats": 70,
      "id": "upload-1771400621250-46",
      "name": "LEKURA LEKAASO",
      "nationalId": "4194436",
      "sheep": 71
    },
    {
      "gender": "Male",
      "goats": 42,
      "id": "upload-1771400621250-47",
      "name": "CHANKO LEMEITARON",
      "nationalId": "26723332",
      "sheep": 43
    },
    {
      "gender": "Male",
      "goats": 40,
      "id": "upload-1771400621250-48",
      "name": "RESMAS LETININA",
      "nationalId": "25609664",
      "sheep": 41
    },
    {
      "gender": "Male",
      "goats": 43,
      "id": "upload-1771400621250-49",
      "name": "EWOI LETIPO",
      "nationalId": "30569782",
      "sheep": 44
    },
    {
      "gender": "Male",
      "goats": 41,
      "id": "upload-1771400621250-50",
      "name": "MOSES LEKIITEI",
      "nationalId": "33941744",
      "sheep": 42
    },
    {
      "gender": "Male",
      "goats": 42,
      "id": "upload-1771400621250-51",
      "name": "MBUGOYAN LERNO",
      "nationalId": "26702679",
      "sheep": 43
    },
    {
      "gender": "Male",
      "goats": 39,
      "id": "upload-1771400621250-52",
      "name": "TIAGAS LENTOJONI",
      "nationalId": "N/A",
      "sheep": 40
    },
    {
      "gender": "Male",
      "goats": 44,
      "id": "upload-1771400621250-53",
      "name": "KIPENO LENENGWESI",
      "nationalId": "36566517",
      "sheep": 45
    },
    {
      "gender": "Male",
      "goats": 41,
      "id": "upload-1771400621250-54",
      "name": "MATIYAN LENKAAKA",
      "nationalId": "31234282",
      "sheep": 42
    },
    {
      "gender": "Male",
      "goats": 42,
      "id": "upload-1771400621250-55",
      "name": "LESUNGAN LEKUPANAI",
      "nationalId": "861052",
      "sheep": 43
    },
    {
      "gender": "Male",
      "goats": 40,
      "id": "upload-1771400621250-56",
      "name": "LEKIRIAMBU LUKUNTE",
      "nationalId": "169223525",
      "sheep": 41
    },
    {
      "gender": "Male",
      "goats": 43,
      "id": "upload-1771400621250-57",
      "name": "SITAAN LEARAMAN",
      "nationalId": "34605264",
      "sheep": 44
    },
    {
      "gender": "Male",
      "goats": 41,
      "id": "upload-1771400621250-58",
      "name": "LIPAMI LETOTO",
      "nationalId": "36823674",
      "sheep": 42
    },
    {
      "gender": "Male",
      "goats": 39,
      "id": "upload-1771400621250-59",
      "name": "MIKE TOIKA LEKARABI",
      "nationalId": "23787972",
      "sheep": 40
    },
    {
      "gender": "Male",
      "goats": 44,
      "id": "upload-1771400621250-60",
      "name": "LMERIANA LEALMUSIA",
      "nationalId": "35551923",
      "sheep": 45
    },
    {
      "gender": "Male",
      "goats": 41,
      "id": "upload-1771400621250-61",
      "name": "KAUS LEALMUSIA",
      "nationalId": "11643120",
      "sheep": 42
    },
    {
      "gender": "Male",
      "goats": 42,
      "id": "upload-1771400621250-62",
      "name": "KALAMA LEKARABI",
      "nationalId": "25970322",
      "sheep": 43
    },
    {
      "gender": "Male",
      "goats": 40,
      "id": "upload-1771400621250-63",
      "name": "MAMPARAN LOLMODONI",
      "nationalId": "24503613",
      "sheep": 41
    },
    {
      "gender": "Male",
      "goats": 43,
      "id": "upload-1771400621250-64",
      "name": "PATRICK LEALMUSIA",
      "nationalId": "41111440",
      "sheep": 44
    },
    {
      "gender": "Male",
      "goats": 41,
      "id": "upload-1771400621250-65",
      "name": "SAMUEL LEMPESIE",
      "nationalId": "13047430",
      "sheep": 42
    },
    {
      "gender": "Male",
      "goats": 42,
      "id": "upload-1771400621250-66",
      "name": "LEMITON LEMPAISIAG",
      "nationalId": "13044404",
      "sheep": 43
    },
    {
      "gender": "Male",
      "goats": 39,
      "id": "upload-1771400621250-67",
      "name": "GABRIEL LESAKALE",
      "nationalId": "20314052",
      "sheep": 40
    },
    {
      "gender": "Male",
      "goats": 41,
      "id": "upload-1771400621250-68",
      "name": "MOSES LEALMUSIA",
      "nationalId": "20314048",
      "sheep": 42
    }
  ],
  "comment": "",
  "county": "Samburu",
  "createdAt": "2026-02-17T17:51:34.111Z",
  "createdBy": "mutai@gmai.com",
  "date": "2025-05-27",
  "femalebeneficiaries": 22,
  "fieldofficers": [
    {
      "name": "Dr.Job Mochama",
      "role": "Veterinary Doctor"
    },
    {
      "name": "Dr.Kevin Lenguris",
      "role": "Veterinary Doctor"
    },
    {
      "name": "Dr.Daniel Waturu",
      "role": "Veterinary Doctor"
    },
    {
      "name": "Dr Borea Lekenit",
      "role": "CDVS (County Director of Veterinary Services"
    },
    {
      "name": "Valentine Chebet",
      "role": "Project Manager"
    },
    {
      "name": "Moses Perialo",
      "role": "Field Officer(Samburu East)"
    }
  ],
  "location": "Lkwasi",
  "malebeneficiaries": 47,
  "programme": "KPMD",
  "status": "completed",
  "subcounty": "Samburu East",
  "vaccines": [
    {
      "doses": 8617,
      "type": "PPR"
    },
    {
      "doses": 8617,
      "type": "CCPP"
    },
    {
      "doses": 8617,
      "type": "Sheep and Goat Pox"
    }
  ]
}